[1,["6c+BsUrsBFjp+I2diwfCeZ@6c48a"],0,[["sp.SkeletonData",["_name","_atlasText","textureNames","_skeletonJson","textures"],-1,3]],[[0,0,1,2,3,4,5]],[[0,"spine_profile_vip","\nspine_profile_vip.png\nsize: 256,128\nformat: RGBA8888\nfilter: Linear,Linear\nrepeat: none\nShaoGuang\n  rotate: false\n  xy: 134, 12\n  size: 50, 34\n  orig: 50, 34\n  offset: 0, 0\n  index: -1\nstar\n  rotate: false\n  xy: 134, 48\n  size: 74, 74\n  orig: 80, 80\n  offset: 4, 4\n  index: -1\nvipbg\n  rotate: false\n  xy: 2, 2\n  size: 130, 120\n  orig: 130, 120\n  offset: 0, 0\n  index: -1\n",["spine_profile_vip.png"],{"skeleton":{"hash":"OCI4dq/HaN0R8s9SGTFu3d4DRyk","spine":"3.6.53","width":200.17,"height":227.68,"images":"./images/"},"bones":[{"name":"root"},{"name":"all","parent":"root"},{"name":"all2","parent":"all","x":-59.93,"y":59.07},{"name":"all3","parent":"all","x":-70.03,"y":-48.64,"shearY":-16.66},{"name":"star","parent":"all","rotation":-51,"x":22.24,"y":-37.59,"scaleX":0.695,"scaleY":0.695}],"slots":[{"name":"vipbg","bone":"all","attachment":"vipbg"},{"name":"star","bone":"star","color":"ffffff00","attachment":"star","blend":"additive"},{"name":"shaoguanga001","bone":"all","attachment":"shaoguanga001"},{"name":"ShaoGuang","bone":"all2","color":"ffffffb4","attachment":"ShaoGuang","blend":"additive"},{"name":"shaoguang2zhezhao","bone":"all","attachment":"shaoguang2zhezhao"},{"name":"ShaoGuang2","bone":"all3","color":"fff0d200","attachment":"ShaoGuang","blend":"additive"}],"skins":{"default":{"ShaoGuang":{"ShaoGuang":{"scaleX":1.063,"scaleY":4.752,"rotation":-44,"width":50,"height":34}},"ShaoGuang2":{"ShaoGuang":{"scaleX":1.174,"scaleY":2.664,"width":50,"height":34}},"shaoguang2zhezhao":{"shaoguang2zhezhao":{"type":"clipping","end":"shaoguang2zhezhao","vertexCount":10,"color":"ce3a3aff","vertices":[-45.18,-30,42.47,-29.58,44.43,-30.34,45.11,-31.08,44.77,-58.44,44.11,-59.16,42.85,-59.64,-43.47,-59.68,-44.81,-59.13,-45.05,-57.86]}},"shaoguanga001":{"shaoguanga001":{"type":"clipping","end":"ShaoGuang","vertexCount":29,"color":"ce3a3aff","vertices":[-49.36,-17.72,-49.05,29.09,-47.83,31.95,-45.48,35.11,-38.95,39.29,-29.98,44.49,-22.22,49.08,-12.64,54.79,-6.31,58.36,-3.76,60,4.5,60,9.78,57.04,20.28,51.02,29.87,45.41,39.77,39.6,45.38,36.13,47.93,33.27,49.46,30.62,50.07,27.76,49.89,-18.65,48.33,-21.98,44.46,-26.3,40.28,-28.74,37.52,-29.76,-37.86,-29.97,-41.32,-27.82,-45,-25.07,-47.85,-21.91,-49.28,-19.67]}},"star":{"star":{"type":"mesh","hull":4,"width":80,"height":80,"uvs":[1,1,0,1,0,0,1,0],"triangles":[1,2,3,1,3,0],"vertices":[38.92,-40.78,-41.08,-40.78,-41.08,39.22,38.92,39.22],"edges":[0,2,2,4,4,6,0,6]}},"vipbg":{"vipbg":{"width":130,"height":120}}}},"animations":{"animation":{"slots":{"ShaoGuang":{"color":[{"time":0,"color":"ffffff00"},{"time":0.2667,"color":"ffffff92"},{"time":1,"color":"ffffff96"},{"time":1.2333,"color":"ffffff00"}]},"ShaoGuang2":{"color":[{"time":1.1667,"color":"ffe7b100"},{"time":1.4333,"color":"fff5e0ff"},{"time":1.9,"color":"fff6e1ff"},{"time":2.1,"color":"ffe7b100"}]},"star":{"color":[{"time":1.7,"color":"ffffff00"},{"time":1.9,"color":"ffffffff"},{"time":2.5,"color":"ffffff00"}]}},"bones":{"all2":{"translate":[{"time":0,"x":-14.68,"y":9.39},{"time":1.2333,"x":136.15,"y":-98.47}]},"all3":{"translate":[{"time":1.1667,"x":-7.04,"y":0},{"time":2.1,"x":127.7,"y":0}]},"star":{"rotate":[{"time":1.7,"angle":81},{"time":2.5,"angle":-39.6}],"scale":[{"time":1.7,"x":1,"y":1},{"time":2.5,"x":0,"y":0,"curve":"stepped"},{"time":6,"x":0,"y":0}]}}}}},[0]]],0,0,[0],[-1],[0]]
