[1,["d78z3xIMRPeb0S5r9Lf7O1@6c48a"],["_textureSource"],["cc.SpriteFrame"],0,[{"name":"icon_dtfl_soccer_0","rect":{"x":17,"y":5,"width":66,"height":66},"offset":{"x":0,"y":0},"originalSize":{"width":100,"height":76},"rotated":false,"capInsets":[0,0,0,0],"vertices":{"rawPosition":[-33,-33,0,33,-33,0,-33,33,0,33,33,0],"indexes":[0,1,2,2,1,3],"uv":[17,71,83,71,17,5,83,5],"nuv":[0.17,0.06578947368421052,0.83,0.06578947368421052,0.17,0.9342105263157895,0.83,0.9342105263157895],"minPos":{"x":-33,"y":-33,"z":0},"maxPos":{"x":33,"y":33,"z":0}},"packable":true,"pixelsToUnit":100,"pivot":{"x":0.5,"y":0.5,"z":0},"meshType":0}],[0],0,[0],[0],[0]]
