[1,["d2Ksq23KlG8pNrLMZy27S7@6c48a"],["_textureSource"],["cc.SpriteFrame"],0,[{"name":"img_aqzx_zwjz_db","rect":{"x":0,"y":0,"width":142,"height":82},"offset":{"x":0,"y":0},"originalSize":{"width":142,"height":82},"rotated":false,"capInsets":[57,35,58,22],"vertices":{"rawPosition":[-71,-41,0,71,-41,0,-71,41,0,71,41,0],"indexes":[0,1,2,2,1,3],"uv":[0,82,142,82,0,0,142,0],"nuv":[0,0,1,0,0,1,1,1],"minPos":{"x":-71,"y":-41,"z":0},"maxPos":{"x":71,"y":41,"z":0}},"packable":true,"pixelsToUnit":100,"pivot":{"x":0.5,"y":0.5,"z":0},"meshType":0}],[0],0,[0],[0],[0]]
