[1,["2bbbHX5hZJL6yYDYc9eP2C@6c48a"],["_textureSource"],["cc.SpriteFrame"],0,[{"name":"comm_icon_jy","rect":{"x":0,"y":0,"width":56,"height":49},"offset":{"x":0,"y":0.5},"originalSize":{"width":56,"height":50},"rotated":false,"capInsets":[0,0,0,0],"vertices":{"rawPosition":[-28,-24.5,0,28,-24.5,0,-28,24.5,0,28,24.5,0],"indexes":[0,1,2,2,1,3],"uv":[0,50,56,50,0,1,56,1],"nuv":[0,0.02,1,0.02,0,1,1,1],"minPos":{"x":-28,"y":-24.5,"z":0},"maxPos":{"x":28,"y":24.5,"z":0}},"packable":true,"pixelsToUnit":100,"pivot":{"x":0.5,"y":0.5,"z":0},"meshType":0}],[0],0,[0],[0],[0]]
